pytest_mpi/__init__.py
pytest_mpi/_helpers.py
pytest_mpi/_version.py
pytest_mpi_tmweigand-0.7.0.dist-info/licenses/LICENSE.txt
pytest_mpi_tmweigand-0.7.0.dist-info/METADATA
pytest_mpi_tmweigand-0.7.0.dist-info/WHEEL
pytest_mpi_tmweigand-0.7.0.dist-info/entry_points.txt
pytest_mpi_tmweigand-0.7.0.dist-info/top_level.txt
pytest_mpi_tmweigand-0.7.0.dist-info/RECORD
