Metadata-Version: 2.4
Name: pytest-mpi-tmweigand
Version: 0.7.0
Summary: forked pytest plugin to collect information from tests
Home-page: https://github.com/tmweigand/pytest-mpi
Author: Timothy M. Weigand
Author-email: timothy.weigand@unc.edu
License: 3-clause BSD
Keywords: pytest testing
Classifier: Framework :: Pytest
Classifier: Development Status :: 3 - Alpha
Classifier: Intended Audience :: Developers
Classifier: License :: OSI Approved :: BSD License
Classifier: Programming Language :: Python :: 3
Classifier: Programming Language :: Python :: 3.5
Classifier: Programming Language :: Python :: 3.6
Classifier: Programming Language :: Python :: 3.7
Classifier: Programming Language :: Python :: 3.8
Classifier: Programming Language :: Python :: 3.9
License-File: LICENSE.txt
Requires-Dist: pytest
Dynamic: author
Dynamic: author-email
Dynamic: classifier
Dynamic: description
Dynamic: home-page
Dynamic: keywords
Dynamic: license
Dynamic: license-file
Dynamic: requires-dist
Dynamic: summary
